pysegul-0.4.1.dist-info/METADATA
pysegul-0.4.1.dist-info/WHEEL
pysegul-0.4.1.dist-info/license_files/LICENSE
pysegul.libs/libgcc_s-e52197c3.so.1
pysegul/__init__.py
pysegul/pysegul.cpython-312-aarch64-linux-musl.so
pysegul-0.4.1.dist-info/RECORD
